MANIFEST.in
README.rst
README.rst~
setup.py
./climson/__init__.py
./climson/climson.py
climson.egg-info/PKG-INFO
climson.egg-info/SOURCES.txt
climson.egg-info/dependency_links.txt
climson.egg-info/not-zip-safe
climson.egg-info/requires.txt
climson.egg-info/top_level.txt
examples/commandfy_example.py
examples/example.py
examples/example.py~
tests/test.py
tests/test.pyc