Metadata-Version: 1.0
Name: climson
Version: 0.1.3
Summary: Commandline tool for easy and simplify to implement applications that is using multi-command CLI.
Home-page: UNKNOWN
Author: takumakanari (chemtrails.t@gmail.com)
Author-email: chemtrails.t@gmail.com
License: UNKNOWN
Keywords: unix,linux,commandline,cli,command,climson
Platform: UNKNOWN
Classifier: Development Status :: 5 - Production/Stable
Classifier: Environment :: Console
Classifier: Intended Audience :: Developers
Classifier: License :: OSI Approved :: MIT License
Classifier: Operating System :: OS Independent
Classifier: Programming Language :: Python
Classifier: Topic :: Utilities
Classifier: Topic :: Software Development :: Libraries :: Python Modules
